scroll.py
stonktrack/__init__.py
stonktrack/__main__.py
stonktrack-1.4.1.dist-info/LICENSE
stonktrack-1.4.1.dist-info/METADATA
stonktrack-1.4.1.dist-info/WHEEL
stonktrack-1.4.1.dist-info/top_level.txt
stonktrack-1.4.1.dist-info/RECORD
