Metadata-Version: 2.1
Name: stonktrack
Version: 1.4.1
Summary: Terminal utility that can track stocks, cryptocurrencies, forexes, and more. Built with Python and urwid.
Home-page: https://github.com/slightlyskepticalpotat/stonktrack
Author: Anthony Chen
License: UNKNOWN
Platform: UNKNOWN
Classifier: Programming Language :: Python :: 3
Classifier: License :: OSI Approved :: GNU Affero General Public License v3
Classifier: Operating System :: OS Independent
Requires-Python: >=3.6
Requires-Dist: pyyaml
Requires-Dist: requests
Requires-Dist: urwid
